autoai_agentrag/__init__.py
autoai_agentrag/agent.py
autoai_agentrag/cli.py
autoai_agentrag/dashboard.py
autoai_agentrag/ml.py
autoai_agentrag/plugins.py
autoai_agentrag/rag.py
autoai_agentrag-0.1.0.dist-info/licenses/LICENSE
autoai_agentrag-0.1.0.dist-info/METADATA
autoai_agentrag-0.1.0.dist-info/WHEEL
autoai_agentrag-0.1.0.dist-info/entry_points.txt
autoai_agentrag-0.1.0.dist-info/top_level.txt
autoai_agentrag-0.1.0.dist-info/RECORD
