Metadata-Version: 2.4
Name: autoai_agentrag
Version: 0.1.0
Summary: AutoAI-AgentRAG: An open-source library integrating AI Agents, RAG, and ML for intelligent automation
Author: AutoAI-AgentRAG Team
License: MIT
Project-URL: Homepage, https://github.com/autoai-agentrag/autoai-agentrag
Project-URL: Bug Tracker, https://github.com/autoai-agentrag/autoai-agentrag/issues
Project-URL: Documentation, https://autoai-agentrag.readthedocs.io
Classifier: Programming Language :: Python :: 3
Classifier: License :: OSI Approved :: MIT License
Classifier: Operating System :: OS Independent
Requires-Python: >=3.8
License-File: LICENSE
Requires-Dist: requests>=2.27.0
Requires-Dist: click>=8.0.0
Requires-Dist: numpy>=1.22.0
Requires-Dist: pandas>=1.4.0
Requires-Dist: pydantic>=2.0.0
Requires-Dist: tqdm>=4.64.0
Requires-Dist: fastapi>=0.95.0
Requires-Dist: uvicorn>=0.20.0
Provides-Extra: dev
Requires-Dist: pytest>=7.0.0; extra == "dev"
Requires-Dist: black>=23.0.0; extra == "dev"
Requires-Dist: isort>=5.10.0; extra == "dev"
Requires-Dist: mypy>=0.991; extra == "dev"
Requires-Dist: flake8>=6.0.0; extra == "dev"
Requires-Dist: sphinx>=6.0.0; extra == "dev"
Requires-Dist: sphinx-rtd-theme>=1.2.0; extra == "dev"
Provides-Extra: ml
Requires-Dist: tensorflow>=2.8.0; extra == "ml"
Requires-Dist: torch>=1.10.0; extra == "ml"
Requires-Dist: transformers>=4.25.0; extra == "ml"
Requires-Dist: langchain>=0.0.267; extra == "ml"
Provides-Extra: all
Requires-Dist: tensorflow>=2.8.0; extra == "all"
Requires-Dist: torch>=1.10.0; extra == "all"
Requires-Dist: transformers>=4.25.0; extra == "all"
Requires-Dist: langchain>=0.0.267; extra == "all"
Requires-Dist: pytest>=7.0.0; extra == "all"
Requires-Dist: black>=23.0.0; extra == "all"
Requires-Dist: isort>=5.10.0; extra == "all"
Requires-Dist: mypy>=0.991; extra == "all"
Requires-Dist: flake8>=6.0.0; extra == "all"
Requires-Dist: sphinx>=6.0.0; extra == "all"
Requires-Dist: sphinx-rtd-theme>=1.2.0; extra == "all"
Dynamic: license-file
